cosinnus_marketplace/__init__.py
cosinnus_marketplace/admin.py
cosinnus_marketplace/apps.py
cosinnus_marketplace/conf.py
cosinnus_marketplace/cosinnus_app.py
cosinnus_marketplace/cosinnus_notifications.py
cosinnus_marketplace/cron.py
cosinnus_marketplace/dashboard.py
cosinnus_marketplace/filters.py
cosinnus_marketplace/forms.py
cosinnus_marketplace/managers.py
cosinnus_marketplace/models.py
cosinnus_marketplace/notify.py
cosinnus_marketplace/search_indexes.py
cosinnus_marketplace/urls.py
cosinnus_marketplace/views.py
cosinnus_marketplace/locale/de/LC_MESSAGES/django.mo
cosinnus_marketplace/locale/de/LC_MESSAGES/django.po
cosinnus_marketplace/locale/en/LC_MESSAGES/django.mo
cosinnus_marketplace/locale/en/LC_MESSAGES/django.po
cosinnus_marketplace/locale/fr/LC_MESSAGES/django.mo
cosinnus_marketplace/locale/fr/LC_MESSAGES/django.po
cosinnus_marketplace/locale/ru/LC_MESSAGES/django.mo
cosinnus_marketplace/locale/ru/LC_MESSAGES/django.po
cosinnus_marketplace/locale/uk/LC_MESSAGES/django.mo
cosinnus_marketplace/locale/uk/LC_MESSAGES/django.po
cosinnus_marketplace/migrations/0001_initial.py
cosinnus_marketplace/migrations/0002_auto_20161017_1544.py
cosinnus_marketplace/migrations/0003_projects_marketplace_inactive.py
cosinnus_marketplace/migrations/0004_auto_20161123_1441.py
cosinnus_marketplace/migrations/__init__.py
cosinnus_marketplace/static/css/cosinnus_marketplace/cosinnus_marketplace.css
cosinnus_marketplace/static/js/cosinnus_marketplace/cosinnus_marketplace.js
cosinnus_marketplace/static/js/vendor/bootstrap.inline.js
cosinnus_marketplace/templates/cosinnus_marketplace/attached_object_select_pill.html
cosinnus_marketplace/templates/cosinnus_marketplace/attached_offers.html
cosinnus_marketplace/templates/cosinnus_marketplace/base.html
cosinnus_marketplace/templates/cosinnus_marketplace/leftnav.html
cosinnus_marketplace/templates/cosinnus_marketplace/list_object.html
cosinnus_marketplace-0.1.dev20180515152431.dist-info/DESCRIPTION.rst
cosinnus_marketplace-0.1.dev20180515152431.dist-info/METADATA
cosinnus_marketplace-0.1.dev20180515152431.dist-info/RECORD
cosinnus_marketplace-0.1.dev20180515152431.dist-info/WHEEL
cosinnus_marketplace-0.1.dev20180515152431.dist-info/metadata.json
cosinnus_marketplace-0.1.dev20180515152431.dist-info/top_level.txt
